dash_resizable_panels/DashResizablePanels.py
dash_resizable_panels/Panel.py
dash_resizable_panels/PanelGroup.py
dash_resizable_panels/PanelResizeHandle.py
dash_resizable_panels/__init__.py
dash_resizable_panels/_imports_.py
dash_resizable_panels/dash_resizable_panels.min.js
dash_resizable_panels/dash_resizable_panels.min.js.map
dash_resizable_panels/metadata.json
dash_resizable_panels/package-info.json
dash_resizable_panels-0.1.0.dist-info/LICENSE
dash_resizable_panels-0.1.0.dist-info/METADATA
dash_resizable_panels-0.1.0.dist-info/WHEEL
dash_resizable_panels-0.1.0.dist-info/top_level.txt
dash_resizable_panels-0.1.0.dist-info/RECORD
