Metadata-Version: 2.1
Name: dash-resizable-panels
Version: 0.1.0
Summary: Dash component for resizable panel groups/layouts
Author: Najeem Muhammed <najeem@gmail.com>
License: MIT
Classifier: Framework :: Dash
License-File: LICENSE
